Workbook

Sheet Room Directory
A1: NABTATECH SOLUTIONS - MEETING ROOM DIRECTORY
A3: Room Name | B3: Room Code | C3: Capacity | D3: Location | E3: Equipment | F3: Hourly Rate (QAR) | G3: Status
A4: Executive Boardroom | B4: CR-EXEC | C4: 20 | D4: Floor 5 - Executive Wing | E4: Projector, Video Conf, Whiteboard, Catering | F4: 500 | G4: Available
A5: Conference Room A | B5: CR-A | C5: 12 | D5: Floor 3 - East Wing | E5: Projector, Video Conf, Whiteboard | F5: 200 | G5: Available
A6: Conference Room B | B6: CR-B | C6: 12 | D6: Floor 3 - West Wing | E6: Projector, Video Conf, Whiteboard | F6: 200 | G6: Available
A7: Meeting Room 1 | B7: MR-1 | C7: 8 | D7: Floor 2 - North | E7: TV Screen, Video Conf | F7: 100 | G7: Available
A8: Meeting Room 2 | B8: MR-2 | C8: 8 | D8: Floor 2 - South | E8: TV Screen, Video Conf | F8: 100 | G8: Available
A9: Meeting Room 3 | B9: MR-3 | C9: 6 | D9: Floor 1 - Reception | E9: TV Screen, Whiteboard | F9: 75 | G9: Available
A10: Training Room | B10: TR-1 | C10: 30 | D10: Floor 4 - Training Center | E10: Projector, 15 Workstations, Whiteboard | F10: 350 | G10: Available
A11: Huddle Space A | B11: HS-A | C11: 4 | D11: Floor 2 - Open Area | E11: TV Screen | F11: 50 | G11: Available
A12: Huddle Space B | B12: HS-B | C12: 4 | D12: Floor 3 - Open Area | E12: TV Screen | F12: 50 | G12: Available
A13: Video Conference Suite | B13: VC-1 | C13: 10 | D13: Floor 4 - IT Wing | E13: Polycom System, Dual Screens | F13: 250 | G13: Available
A16: ROOM SUMMARY
A17: Total Rooms: | B17: =COUNTA(A4:A13)
A18: Total Capacity: | B18: =SUM(C4:C13)
A19: Available Rooms: | B19: =COUNTIF(G4:G13,"Available")
A20: Average Hourly Rate: | B20: =AVERAGE(F4:F13)

Sheet Weekly Calendar
A1: MEETING ROOM WEEKLY CALENDAR | I1: QUICK BOOKING FORM
A3: Week Starting: | B3: 46069 | D3: Room: | E3: Conference Room A | I3: Meeting Title:
A4: Legend: | B4: Free | C4: Booked | D4: Pending | E4: Completed | I4: Room: | J4: Conference Room A
I5: Date:
A6: Time | B6: Monday 16 Feb | C6: Tuesday 17 Feb | D6: Wednesday 18 Feb | E6: Thursday 19 Feb | F6: Friday 20 Feb | I6: Start Time:
A7: 08:00 | B7: IT Team Meeting | C7: Available | D7: Available | E7: Board Meeting | F7: Available | I7: End Time:
A8: 09:00 | B8: IT Team Meeting | C8: Available | D8: Available | E8: Board Meeting | F8: Available | I8: Booked By:
A9: 10:00 | B9: Available | C9: Client Presentation | D9: Available | E9: Board Meeting | F9: Finance Review | I9: Department:
A10: 11:00 | B10: Available | C10: Client Presentation | D10: Available | E10: Board Meeting | F10: Finance Review | I10: Attendees:
A11: 12:00 | B11: Available | C11: Client Presentation | D11: Available | E11: Available | F11: Available | I11: Purpose:
A12: 13:00 | B12: Available | C12: Available | D12: HR Interview | E12: Available | F12: Available | I12: Equipment Needed:
A13: 14:00 | B13: Available | C13: Available | D13: HR Interview | E13: Available | F13: Project Kickoff | I13: Catering Required: | J13: No
A14: 15:00 | B14: Available | C14: Available | D14: Available | E14: Training Session | F14: Project Kickoff | I14: Status: | J14: Pending
A15: 16:00 | B15: Available | C15: Available | D15: Available | E15: Training Session | F15: Available
A16: 17:00 | B16: Available | C16: Available | D16: Available | E16: Training Session | F16: Available
A17: 18:00 | B17: Available | C17: Available | D17: Available | E17: Available | F17: Available

Sheet Booking Log
A1: MEETING ROOM BOOKING LOG
A3: Booking ID | B3: Room | C3: Date | D3: Start Time | E3: End Time | F3: Duration (hrs) | G3: Booked By | H3: Department | I3: Purpose | J3: Attendees | K3: Status | L3: Cost (QAR)
A4: BK-2026-001 | B4: Conference Room A | C4: 2026-02-10 | D4: 09:00 | E4: 11:00 | F4: 2 | G4: Ahmed Hassan | H4: IT | I4: Project Review | J4: 8 | K4: Completed | L4: 400
A5: BK-2026-002 | B5: Executive Boardroom | C5: 2026-02-10 | D5: 14:00 | E5: 16:00 | F5: 2 | G5: CEO Office | H5: Management | I5: Board Meeting | J5: 15 | K5: Completed | L5: 1000
A6: BK-2026-003 | B6: Meeting Room 1 | C6: 2026-02-11 | D6: 10:00 | E6: 11:00 | F6: 1 | G6: Sara Ibrahim | H6: HR | I6: Interview | J6: 3 | K6: Completed | L6: 100
A7: BK-2026-004 | B7: Training Room | C7: 2026-02-11 | D7: 09:00 | E7: 17:00 | F7: 8 | G7: IT Training | H7: IT | I7: Azure Workshop | J7: 25 | K7: Completed | L7: 2800
A8: BK-2026-005 | B8: Conference Room B | C8: 2026-02-12 | D8: 13:00 | E8: 15:00 | F8: 2 | G8: Finance Team | H8: Finance | I8: Budget Review | J8: 6 | K8: Completed | L8: 400
A9: BK-2026-006 | B9: Video Conference Suite | C9: 2026-02-12 | D9: 10:00 | E9: 12:00 | F9: 2 | G9: Sales Team | H9: Sales | I9: Client Call | J9: 4 | K9: Completed | L9: 500
A10: BK-2026-007 | B10: Huddle Space A | C10: 2026-02-13 | D10: 14:00 | E10: 15:00 | F10: 1 | G10: Dev Team | H10: IT | I10: Sprint Planning | J10: 4 | K10: Completed | L10: 50
A11: BK-2026-008 | B11: Conference Room A | C11: 2026-02-13 | D11: 09:00 | E11: 12:00 | F11: 3 | G11: Marketing | H11: Marketing | I11: Campaign Planning | J11: 7 | K11: Completed | L11: 600
A12: BK-2026-009 | B12: Meeting Room 2 | C12: 2026-02-14 | D12: 11:00 | E12: 12:00 | F12: 1 | G12: Legal Team | H12: Legal | I12: Contract Review | J12: 3 | K12: Completed | L12: 100
A13: BK-2026-010 | B13: Executive Boardroom | C13: 2026-02-14 | D13: 14:00 | E13: 17:00 | F13: 3 | G13: CEO Office | H13: Management | I13: Strategy Session | J13: 12 | K13: Completed | L13: 1500
A14: BK-2026-011 | B14: Conference Room A | C14: 2026-02-16 | D14: 09:00 | E14: 11:00 | F14: 2 | G14: IT Team | H14: IT | I14: Team Meeting | J14: 10 | K14: Confirmed | L14: 400
A15: BK-2026-012 | B15: Training Room | C15: 2026-02-17 | D15: 09:00 | E15: 17:00 | F15: 8 | G15: HR Training | H15: HR | I15: Onboarding | J15: 20 | K15: Confirmed | L15: 2800
... A18: BK-2026-015 | B18: Video Conference Suite | C18: 2026-02-18 | D18: 15:00 | E18: 17:00 | F18: 2 | G18: Sales | H18: Sales | I18: Demo Call | J18: 4 | K18: Pending | L18: 500
A20: SUMMARY
A21: Total Bookings: | B21: =COUNTA(A4:A18)
A22: Completed: | B22: =COUNTIF(K4:K18,"Completed")
A23: Confirmed: | B23: =COUNTIF(K4:K18,"Confirmed")
A24: Pending: | B24: =COUNTIF(K4:K18,"Pending")
A25: Total Revenue: | B25: =SUM(L4:L18)
A26: Avg Duration (hrs): | B26: =AVERAGE(F4:F18)

Sheet Analytics
A1: MEETING ROOM ANALYTICS
A3: KEY PERFORMANCE INDICATORS
A4: Total Bookings (MTD): | B4: =COUNTIFS('Booking Log'!C:C,">="&DATE(YEAR(TODAY()),MONTH(TODAY()),1))
A5: Room Utilization Rate: | B5: =IFERROR(COUNTIF('Booking Log'!K:K,"Completed")/COUNTA('Booking Log'!A:A)*100,0)
A6: Average Booking Duration: | B6: =AVERAGE('Booking Log'!F:F)
A7: Total Revenue (MTD): | B7: =SUMIFS('Booking Log'!L:L,'Booking Log'!C:C,">="&DATE(YEAR(TODAY()),MONTH(TODAY()),1))
A8: Most Popular Room: | B8: =INDEX('Booking Log'!B:B,MATCH(MAX(COUNTIF('Booking Log'!B:B,'Booking Log'!B:B)),COUNTIF('Booking Log'!B:B,'Booking Log'!B:B),0))
A9: Cancellation Rate: | B9: =IFERROR(COUNTIF('Booking Log'!K:K,"Cancelled")/COUNTA('Booking Log'!A:A)*100,0)
A12: BOOKINGS BY ROOM
A13: Room | B13: Bookings | C13: Revenue
A14: Conference Room A | B14: =COUNTIF('Booking Log'!B:B,A14) | C14: =SUMIF('Booking Log'!B:B,A14,'Booking Log'!L:L)
A15: Conference Room B | B15: =COUNTIF('Booking Log'!B:B,A15) | C15: =SUMIF('Booking Log'!B:B,A15,'Booking Log'!L:L)
A16: Executive Boardroom | B16: =COUNTIF('Booking Log'!B:B,A16) | C16: =SUMIF('Booking Log'!B:B,A16,'Booking Log'!L:L)
A17: Meeting Room 1 | B17: =COUNTIF('Booking Log'!B:B,A17) | C17: =SUMIF('Booking Log'!B:B,A17,'Booking Log'!L:L)
A18: Meeting Room 2 | B18: =COUNTIF('Booking Log'!B:B,A18) | C18: =SUMIF('Booking Log'!B:B,A18,'Booking Log'!L:L)
A19: Training Room | B19: =COUNTIF('Booking Log'!B:B,A19) | C19: =SUMIF('Booking Log'!B:B,A19,'Booking Log'!L:L)
A20: Video Conference Suite | B20: =COUNTIF('Booking Log'!B:B,A20) | C20: =SUMIF('Booking Log'!B:B,A20,'Booking Log'!L:L)
A21: Huddle Space A | B21: =COUNTIF('Booking Log'!B:B,A21) | C21: =SUMIF('Booking Log'!B:B,A21,'Booking Log'!L:L)
A24: BOOKINGS BY DEPARTMENT
A25: Department | B25: Bookings
A26: IT | B26: =COUNTIF('Booking Log'!H:H,A26)
A27: HR | B27: =COUNTIF('Booking Log'!H:H,A27)
A28: Management | B28: =COUNTIF('Booking Log'!H:H,A28)
A29: Finance | B29: =COUNTIF('Booking Log'!H:H,A29)
A30: Sales | B30: =COUNTIF('Booking Log'!H:H,A30)
A31: Marketing | B31: =COUNTIF('Booking Log'!H:H,A31)
A32: Legal | B32: =COUNTIF('Booking Log'!H:H,A32)
